{
  "generated_at": "2026-03-31T08:46:10.248198",
  "count": 12,
  "dropped_count": 20,
  "items": [
    {
      "title": "上海：2025年实现生产总值56708.71亿元",
      "url": "https://jnzstatic.cs.com.cn/zzb/htmlInfo/118257.html",
      "source": "cs_news",
      "published_at": null
    },
    {
      "title": "市场监管总局：着力防治光伏、锂电池等重点行业和领域“内卷式”竞争",
      "url": "https://jnzstatic.cs.com.cn/zzb/htmlInfo/118246.html",
      "source": "cs_news",
      "published_at": null
    },
    {
      "title": "生态环境部：大力推进非电行业超低排放技术研发，推动常规污染物与非常规污染物高效协同减排",
      "url": "https://jnzstatic.cs.com.cn/zzb/htmlInfo/118233.html",
      "source": "cs_news",
      "published_at": null
    },
    {
      "title": "生态环境部：有序推进重大科技攻关任务 加快推动战略科技力量建设",
      "url": "https://jnzstatic.cs.com.cn/zzb/htmlInfo/118232.html",
      "source": "cs_news",
      "published_at": null
    },
    {
      "title": "商务部：第六届消博会参展国际展品占比65%，较去年提升20个百分点 商务部副部长盛秋平3月30日在国新办新闻发布会上表示，第六届消博会将于今年4月13日至18日在海南省举办。本届消博会既是“十五五”开局之年我国重大展会的“首展”，也是海南自贸港全岛封关运作以后的“首秀”。本届消...",
      "url": "https://jnzstatic.cs.com.cn/zzb/htmlInfo/118227.html",
      "source": "cs_news",
      "published_at": null
    },
    {
      "title": "商务部：截至目前已有70余家头部企业在参加消博会以后落户海南 商务部副部长盛秋平3月30日在国新办新闻发布会上表示，消博会已成为海南自贸港建设的“加速器”。五年来，消博会全方位、多角度、立体化展现海南自贸港建设的改革突破与丰硕成果，展示制度型开放稳步推进、营商环境持续...",
      "url": "https://jnzstatic.cs.com.cn/zzb/htmlInfo/118226.html",
      "source": "cs_news",
      "published_at": null
    },
    {
      "title": "交通运输部等四部门：到2027年实现人工智能技术与航运要素广泛深度融合",
      "url": "https://jnzstatic.cs.com.cn/zzb/htmlInfo/118223.html",
      "source": "cs_news",
      "published_at": null
    },
    {
      "title": "【预告】中国贸促会31日召开新闻发布会，事关第四届链博会筹备进展等",
      "url": "https://jnzstatic.cs.com.cn/zzb/htmlInfo/118222.html",
      "source": "cs_news",
      "published_at": null
    },
    {
      "title": "国家能源局：2月底全国累计发电装机容量39.5亿千瓦 同比增长15.9%",
      "url": "http://video.cs.com.cn/178/7810.shtml?id=7810",
      "source": "cs_news",
      "published_at": null
    },
    {
      "title": "六部门：稳步推进农村供水价格改革",
      "url": "http://video.cs.com.cn/178/7809.shtml?id=7809",
      "source": "cs_news",
      "published_at": null
    },
    {
      "title": "北方稀土拟取消每月挂牌价？公司最新回应：消息属实",
      "url": "http://video.cs.com.cn/150/7561.shtml?id=7561",
      "source": "cs_news",
      "published_at": null
    },
    {
      "title": "培育钻石掀涨价潮？上市公司最新回应",
      "url": "http://video.cs.com.cn/150/7560.shtml?id=7560",
      "source": "cs_news",
      "published_at": null
    }
  ],
  "dropped_examples": [
    {
      "title": "山东数字人科技股份有限公司2025年度网上业绩说明会",
      "url": "https://rs.cs.com.cn/dist/#/index?id=c6dadf60c0ce286eed890259d7196c5d"
    },
    {
      "title": "视涯科技股份有限公司首次公开发行A股上市仪式",
      "url": "https://www.cs.com.cn/roadshow/sse/688781/lc/"
    },
    {
      "title": "山东悦龙橡塑科技股份有限公司向不特定合格投资者公开发行股票并在北交所上市网上路演",
      "url": "https://www.cs.com.cn/roadshow/bse/ylkj/ipo/"
    },
    {
      "title": "山东沃华医药科技股份有限公司2025年度业绩说明会",
      "url": "https://www.cs.com.cn/roadshow/szse/002107/pb261/"
    },
    {
      "title": "宁波富邦精业集团股份有限公司2025年第三季度业绩说明会",
      "url": "https://www.cs.com.cn/roadshow/sse/600768/pb253/"
    },
    {
      "title": "普联软件股份有限公司向不特定对象发行可转换公司债券网上路演",
      "url": "https://www.cs.com.cn/roadshow/szse/300996/rf251/"
    },
    {
      "title": "宁波市天普橡胶科技股份有限公司关于控制权转让事项的投资者说明会",
      "url": "https://www.cs.com.cn/roadshow/sse/605255/pb252/index.html"
    },
    {
      "title": "2025公募基金高质量发展大会暨第22届基金业金牛奖颁奖典礼",
      "url": "https://www.cs.com.cn/jnj/jnjj/jjy2025/"
    },
    {
      "title": "2025科创投资大会",
      "url": "https://www.cs.com.cn/jnj/gqtzjnj/gqjn2025/"
    },
    {
      "title": "2025量化行业高质量发展大会",
      "url": "https://www.cs.com.cn/jnj/jnfx/qt2025/"
    },
    {
      "title": "2025年金牛企业可持续发展论坛",
      "url": "https://www.cs.com.cn/jnj/ESG/esg2025/"
    },
    {
      "title": "2025证券业高质量发展大会",
      "url": "https://www.cs.com.cn/jnj/jnfx/zqy2025/"
    },
    {
      "title": "2025厦门产业发展大会暨上市公司（港股）金牛奖颁奖典礼",
      "url": "https://www.cs.com.cn/jnj/gg/ggjn2025/"
    },
    {
      "title": "2025上市公司高质量发展论坛",
      "url": "https://www.cs.com.cn/jnj/jngs/ssgs2025/"
    },
    {
      "title": "全国社保基金理事会",
      "url": "http://www.ssf.gov.cn/portal/index.htm"
    },
    {
      "title": "中国金融期货交易所",
      "url": "http://www.cffex.com.cn/"
    },
    {
      "title": "中国证券登记结算公司",
      "url": "http://www.chinaclear.cn/"
    },
    {
      "title": "中国上市公司协会",
      "url": "https://www.capco.org.cn/"
    },
    {
      "title": "中国证券投资基金业协会",
      "url": "https://www.amac.org.cn/"
    },
    {
      "title": "京ICP备12041706号-1",
      "url": "https://beian.miit.gov.cn/#/Integrated/index"
    }
  ]
}